3/Display.v

module Display(CLK, RST, Winner_DISP, A_DISP, B_DISP, C_DISP);
    input CLK, RST;
    input [2:0] Winner_DISP;
    input A_DISP, B_DISP, C_DISP;

    reg[5:0] Clock; //클락신호 카운트하는 변수

    

    always @ (posedge CLK) begin //상승엣지일때
        
        if(RST == 0)begin
            if(Winner_DISP == 3'b000)begin //승부가결정 안되었을 때
                $display("[#%d] A : %b B : %b  C : %b\n\n", Clock,A_DISP,B_DISP,C_DISP); 
            end
            else begin //승부가 결정되었을 때
                case(Winner_DISP) //승부에 따라서 출력
                3'b001 : $display("[#%d] Result : Winner is C\n\n", Clock);
                3'b010 : $display("[#%d] Result : Winner is B\n\n", Clock);
                3'b011 : $display("[#%d] Result : Winner is B and C\n\n", Clock);
                3'b100 : $display("[#%d] Result : Winner is A\n\n", Clock,);
                3'b101 : $display("[#%d] Result : Winner is A and C\n\n", Clock);
                3'b110 : $display("[#%d] Result : Winner is A and B\n\n", Clock);
                3'b111 : $display("[#%d] Result : DRAW\n\n", Clock);
                endcase
                
            end
        Clock++; //카운트 +1 (0초는 초기화상태일때)
        end
        else begin
            Clock = 0; //RST이 1일때 카운트 초기화
        end
        
    end    
endmodule

3/HGame.v
module HGame ( CLK, RST, A, B, C, Winner_DISP, A_DISP, B_DISP, C_DISP);
input CLK, RST, A,B,C;
output reg [2:0] Winner_DISP;
output reg A_DISP, B_DISP, C_DISP;


	reg [3:0] status; // state값을 저장하는 변수 선언
	parameter S_INIT = 0;  //state를 파라미터로 선언
	parameter S_AS = 1; 
  parameter S_BS = 2;
  parameter S_CS = 3;
  parameter S_AW = 4;
  parameter S_BW = 5;
  parameter S_CW = 6;
  parameter S_ABW = 7;
  parameter S_ACW= 8;
  parameter S_BCW = 9;
  parameter S_DRAW = 10;



    always @(posedge CLK) begin  
      if(RST == 1) begin  //RST이 1일때 초기화
        status <= S_INIT; //status 설정
        {A_DISP, B_DISP, C_DISP} <= 3'b000; //DISP값 초기화
        Winner_DISP <= 3'b000; //승부 결정 변수 초기화
      end

      case (status) //status에 따라서 case 실행
        S_INIT : begin //INIT 일때
          Winner_DISP <= 3'b000; 

          case ({A, B, C}) //입력값에 따라서 case 실행, DISP 값을 넣어주고 status를 바꾼다
          3'b000 : status <= S_INIT;
          3'b001 : begin 
            status <= S_CS;
            A_DISP <= 0;
            B_DISP <= 0;
            C_DISP <= 1;
          end
          3'b010 : begin 
            status <= S_BS;
            A_DISP <= 0;
            B_DISP <= 1;
            C_DISP <= 0;
          end
          3'b011 : begin 
            status <= S_AW;
            A_DISP <= 0;
            B_DISP <= 1;
            C_DISP <= 1;
          end
          3'b100 : begin 
            status <= S_AS;
            A_DISP <= 1;
            B_DISP <= 0;
            C_DISP <= 0;
          end
          3'b101 : begin 
            status <= S_BW;
            A_DISP <= 1;
            B_DISP <= 0;
            C_DISP <= 1;
          end
          3'b110 : begin 
            status <= S_CW;
            A_DISP <= 1;
            B_DISP <= 1;
            C_DISP <= 0;
          end
          3'b111 : begin 
            status <= S_DRAW;
            A_DISP <= 1;
            B_DISP <= 1;
            C_DISP <= 1;
          end
          endcase 
        end


        S_AS : begin //A가 일어선 상태이며, 아직 승부가 결정 안된 경우
          case ({A, B, C}) 
          3'b000 : status <= S_AS;
          3'b001 : begin 
            status <= S_ACW;
            A_DISP <= 0;
            B_DISP <= 0;
            C_DISP <= 1;
          end
          3'b010 : begin 
            status <= S_ABW;
            A_DISP <= 0;
            B_DISP <= 1;
            C_DISP <= 0;
          end
          3'b011 : begin 
            status <= S_AW;
            A_DISP <= 0;
            B_DISP <= 1;
            C_DISP <= 1;
          end
          3'b100 : begin 
            status <= S_AS;
            A_DISP <= 1;
            B_DISP <= 0;
            C_DISP <= 0;
          end
          3'b101 : begin 
            status <= S_ACW;
            A_DISP <= 1;
            B_DISP <= 0;
            C_DISP <= 1;
          end
          3'b110 : begin 
            status <= S_ABW;
            A_DISP <= 1;
            B_DISP <= 1;
            C_DISP <= 0;
          end
          3'b111 : begin 
            status <= S_AW;
            A_DISP <= 1;
            B_DISP <= 1;
            C_DISP <= 1;
          end
          endcase 
        end

        S_BS : begin //B가 일어선 상태이며, 아직 승부가 결정 안된 경우
          case ({A, B, C}) 
          3'b000 : status <= S_BS;
          3'b001 : begin 
            status <= S_BCW;
            A_DISP <= 0;
            B_DISP <= 0;
            C_DISP <= 1;
          end
          3'b010 : begin 
            status <= S_BS;
            A_DISP <= 0;
            B_DISP <= 1;
            C_DISP <= 0;
          end
          3'b011 : begin 
            status <= S_BCW;
            A_DISP <= 0;
            B_DISP <= 1;
            C_DISP <= 1;
          end
          3'b100 : begin 
            status <= S_ABW;
            A_DISP <= 1;
            B_DISP <= 0;
            C_DISP <= 0;
          end
          3'b101 : begin 
            status <= S_BW;
            A_DISP <= 1;
            B_DISP <= 0;
            C_DISP <= 1;
          end
          3'b110 : begin 
            status <= S_ABW;
            A_DISP <= 1;
            B_DISP <= 1;
            C_DISP <= 0;
          end
          3'b111 : begin 
            status <= S_BW;
            A_DISP <= 1;
            B_DISP <= 1;
            C_DISP <= 1;
          end
          endcase 
        end

        S_CS : begin //C가 일어선 상태이며, 아직 승부가 결정 안된 경우
          case ({A, B, C}) 
          3'b000 : status <= S_CS;
          3'b001 : begin 
            status <= S_CS;
            A_DISP <= 0;
            B_DISP <= 0;
            C_DISP <= 1;
          end
          3'b010 : begin 
            status <= S_BCW;
            A_DISP <= 0;
            B_DISP <= 1;
            C_DISP <= 0;
          end
          3'b011 : begin 
            status <= S_BCW;
            A_DISP <= 0;
            B_DISP <= 1;
            C_DISP <= 1;
          end
          3'b100 : begin 
            status <= S_ACW;
            A_DISP <= 1;
            B_DISP <= 0;
            C_DISP <= 0;
          end
          3'b101 : begin 
            status <= S_ACW;
            A_DISP <= 1;
            B_DISP <= 0;
            C_DISP <= 1;
          end
          3'b110 : begin 
            status <= S_CW;
            A_DISP <= 1;
            B_DISP <= 1;
            C_DISP <= 0;
          end
          3'b111 : begin 
            status <= S_CW;
            A_DISP <= 1;
            B_DISP <= 1;
            C_DISP <= 1;
          end
          endcase 
        end

        S_AW : begin //A가 이겼을 때, 이하 동일 
          Winner_DISP <= 3'b100;
          status <= S_INIT;
          {A_DISP, B_DISP, C_DISP} <= 3'b000; 
        end
        S_BW : begin 
          Winner_DISP <= 3'b010;
          status <= S_INIT;
          {A_DISP, B_DISP, C_DISP} <= 3'b000;
        end
        S_CW : begin
          Winner_DISP <= 3'b001;
          status <= S_INIT;
          {A_DISP, B_DISP, C_DISP} <= 3'b000;
        end
        S_ABW : begin
          Winner_DISP <= 3'b110;
          status <= S_INIT;
          {A_DISP, B_DISP, C_DISP} <= 3'b000;
        end
        S_BCW : begin
          Winner_DISP <= 3'b011;
          status <= S_INIT;
          {A_DISP, B_DISP, C_DISP} <= 3'b000;
        end
        S_ACW : begin
          Winner_DISP <= 3'b101;
          status <= S_INIT;
          {A_DISP, B_DISP, C_DISP} <= 3'b000;
        end
        S_DRAW : begin
          Winner_DISP <= 3'b111;
          status <= S_INIT;
          {A_DISP, B_DISP, C_DISP} <= 3'b000;
        end

      endcase

      
    end
  
endmodule

3/HGameTb.v
`timescale 1 ns / 100 ps   

module HGameTb();

    reg CLK, RST, A, B, C; //입력

    wire A_DISP, B_DISP, C_DISP; //출력
    wire [2:0] Winner_DISP;


    HGame UUT1(CLK, RST, A, B, C, Winner_DISP, A_DISP, B_DISP, C_DISP); 
    Display UUT2(CLK, RST, Winner_DISP, A_DISP, B_DISP, C_DISP);


    initial begin //클락신호 초기화
        
        CLK = 1;
    end

    always begin //클락신호 생성
        #1
        CLK = ~CLK;
        
    end

    initial begin       
        $dumpfile("test.vcd"); //test파일 생성
        $dumpvars(0, HGameTb); 
        RST = 1; //초기화를 위해 신호 1로
        #2
        RST = 0; //초기화 신호 다시 0으로 
        A = 1; B = 1; C= 1; //DRAW
        #2

        #2


        A = 0; B = 1; C= 1; //Awin
        #2

        #2

        A = 1; B = 0; C= 1; //Bwin
        #2

        #2


        A = 1; B = 1; C= 0; //Cwin
        #2

        #2

        A = 1; B = 0; C= 0; 
        #2
        A = 0; B = 1; C= 1; // Awin

        #2

        #2        

        A = 0; B = 1; C = 0 ; 
        #2
        A = 1; B = 0; C = 1; // Bwin

        #2

        #2 

        A = 0; B = 0; C= 1; 
        #2
        A = 1; B = 1; C= 0; // Cwin

        #2

        #2                 

        A = 1; B = 0; C= 0; 
        #2
        A = 0; B = 1; C= 0; // ABwin

        #2

        #2

        A = 1; B = 0; C= 0; 
        #2
        A = 0; B = 0; C= 1; // ACwin

        #2

        #2

        A = 0; B = 1; C= 0; 
        #2
        A = 0; B = 0; C= 1;// BCwin
        #2

        #2

        A = 0; B = 0; C= 0; 
        #2
        A = 0; B = 0; C= 0;
        #2
        A = 0; B = 0; C= 0;
        #2
        A = 1; B = 1; C= 1;
        #2 

        #2
        $finish;
    end
    

endmodule

3/test.vcd
$date
	Wed May  4 16:43:01 2022
$end
$version
	Icarus Verilog
$end
$timescale
	100ps
$end
$scope module HGameTb $end
$var wire 3 ! Winner_DISP [2:0] $end
$var wire 1 " C_DISP $end
$var wire 1 # B_DISP $end
$var wire 1 $ A_DISP $end
$var reg 1 % A $end
$var reg 1 & B $end
$var reg 1 ' C $end
$var reg 1 ( CLK $end
$var reg 1 ) RST $end
$scope module UUT1 $end
$var wire 1 % A $end
$var wire 1 & B $end
$var wire 1 ' C $end
$var wire 1 ( CLK $end
$var wire 1 ) RST $end
$var reg 1 $ A_DISP $end
$var reg 1 # B_DISP $end
$var reg 1 " C_DISP $end
$var reg 3 * Winner_DISP [2:0] $end
$var reg 4 + status [3:0] $end
$upscope $end
$scope module UUT2 $end
$var wire 1 $ A_DISP $end
$var wire 1 # B_DISP $end
$var wire 1 ( CLK $end
$var wire 1 " C_DISP $end
$var wire 1 ) RST $end
$var wire 3 , Winner_DISP [2:0] $end
$var reg 6 - Clock [5:0] $end
$upscope $end
$upscope $end
$enddefinitions $end
#0
$dumpvars
b0 -
b0 ,
b0 +
b0 *
1)
1(
x'
x&
x%
0$
0#
0"
b0 !
$end
#10
0(
#20
1"
1#
1$
b1010 +
b1 -
1(
1'
1&
1%
0)
#30
0(
#40
0$
0#
0"
b0 +
b111 !
b111 *
b111 ,
b10 -
1(
#50
0(
#60
1"
1#
b100 +
b0 !
b0 *
b0 ,
b11 -
1(
0%
#70
0(
#80
0#
0"
b0 +
b100 !
b100 *
b100 ,
b100 -
1(
#90
0(
#100
1"
1$
b101 +
b0 !
b0 *
b0 ,
b101 -
1(
0&
1%
#110
0(
#120
0$
0"
b0 +
b10 !
b10 *
b10 ,
b110 -
1(
#130
0(
#140
1#
1$
b110 +
b0 !
b0 *
b0 ,
b111 -
1(
0'
1&
#150
0(
#160
0$
0#
b0 +
b1 !
b1 *
b1 ,
b1000 -
1(
#170
0(
#180
1$
b1 +
b0 !
b0 *
b0 ,
b1001 -
1(
0&
#190
0(
#200
1"
1#
0$
b100 +
b1010 -
1(
1'
1&
0%
#210
0(
#220
0#
0"
b0 +
b100 !
b100 *
b100 ,
b1011 -
1(
#230
0(
#240
1#
b10 +
b0 !
b0 *
b0 ,
b1100 -
1(
0'
#250
0(
#260
1"
0#
1$
b101 +
b1101 -
1(
1'
0&
1%
#270
0(
#280
0$
0"
b0 +
b10 !
b10 *
b10 ,
b1110 -
1(
#290
0(
#300
1"
b11 +
b0 !
b0 *
b0 ,
b1111 -
1(
0%
#310
0(
#320
0"
1#
1$
b110 +
b10000 -
1(
0'
1&
1%
#330
0(
#340
0$
0#
b0 +
b1 !
b1 *
b1 ,
b10001 -
1(
#350
0(
#360
1$
b1 +
b0 !
b0 *
b0 ,
b10010 -
1(
0&
#370
0(
#380
1#
0$
b111 +
b10011 -
1(
1&
0%
#390
0(
#400
0#
b0 +
b110 !
b110 *
b110 ,
b10100 -
1(
#410
0(
#420
1$
b1 +
b0 !
b0 *
b0 ,
b10101 -
1(
0&
1%
#430
0(
#440
1"
0$
b1000 +
b10110 -
1(
1'
0%
#450
0(
#460
0"
b0 +
b101 !
b101 *
b101 ,
b10111 -
1(
#470
0(
#480
1#
b10 +
b0 !
b0 *
b0 ,
b11000 -
1(
0'
1&
#490
0(
#500
1"
0#
b1001 +
b11001 -
1(
1'
0&
#510
0(
#520
0"
b0 +
b11 !
b11 *
b11 ,
b11010 -
1(
#530
0(
#540
b0 !
b0 *
b0 ,
b11011 -
1(
0'
#550
0(
#560
b11100 -
1(
#570
0(
#580
b11101 -
1(
#590
0(
#600
1"
1#
1$
b1010 +
b11110 -
1(
1'
1&
1%
#610
0(
#620
0$
0#
0"
b0 +
b111 !
b111 *
b111 ,
b11111 -
1(
#630
0(
#640
1"
1#
1$
b1010 +
b0 !
b0 *
b0 ,
1(
