2/FPAdd.v
module FPAdd(
input [9:0] A,
input [9:0] B,
output [9:0] Out,
output Cout
);
wire [5:0] MA; //A의 마티사 부분
wire [5:0] MB; //B의 마티사 부분
wire [5:0] MO; //덧셈결과 마티사부분
wire [5:0] MB1; //쉬푸트 돌리고 덧셈로 들어갈 마티사 B

wire [3:0] EA; //A의 지수부분
wire [3:0] EB; //B의 지수부분
wire [3:0] EO; //덧셈결과 지수부분
wire [3:0] E1; 


wire [9:0] FA; //쉬프트 결과 값 저장
wire [9:0] FB; //쉬프트 결과 값 저장 

wire [9:0] FO; //쉬프트 결과 할 값 저장

assign MA[5:0] = A[5:0]; //알맞게 그 값을 대입 시켜준다
assign MB[5:0] = B[5:0];

assign EA = A[9:6]; //지수 부분도 그와 맞게 대입시켜준다.
assign EB = B[9:6];
assign EO = 4'b1001;
assign MB1 = FB[5:0];

wire [3:0] num1,num5; // 쉬프트 값을 대입해줄 변수설정

assign num1 = EA - EB; //지수부분 A-B에서 빼준 값을 넣어준다.
myshifter Bshi(B, num1,FB);

//num1만큼 쉬프트 해준다.

adder abadder(MA,MB1,MO,Cout);

assign num5 = ((Cout) ? 4'b0001 : 4'b0000); //num5에 캐리아웃이 1이면 1값 아니면 0값을 저장시켜준다.
//참이라면 1을 더해주고 1을 쉬프트할것이며 아니면 0을 더해줄것이다.
assign E1 = EO + num5;
assign FO = {E1,MO};
//이제 Out값을 쉬프트 해준다.
myshifter Oshi(FO,num5,Out); 
endmodule

module myshifter(Din, num ,Dout);
input [9:0] Din; // 데이터 인풋값
input [3:0] num; //쉬프트 amount
output [9:0] Dout; //쉬프트 값 출력

reg[9:0] Dout,x1,x2,x3,x4,x5,x6,x7,x8,x9;

always @ (Din or num) begin
if( num == 1) x1 = {1'b0 , Din[9:1]}; else x1=Din;
if( num == 2) x2 = {2'b00 , Din[9:2]}; else x2=x1;
if( num == 3) x3 = {3'b000 , Din[9:3]}; else x3=x2;
if( num == 4) x4 = {4'b0000 , Din[9:4]}; else x4=x3;
if( num == 5) x5 = {5'b00000 , Din[9:5]}; else x5=x4;
if( num == 6) x6 = {6'b000000 , Din[9:6]}; else x6=x5;
if( num == 7) x7 = {7'b0000000 , Din[9:7]}; else x7=x6;
if( num == 8) x8 = {8'b00000000 , Din[9:8]}; else x8=x7;
if( num == 9) x9 = {9'b000000000 , Din[9]}; else x9=x8;
if( num >= 10 && num < 15 ) Dout = {10'b0000000000}; else Dout = x9;
//10과 15사이의 쉬프트값은 모두 어차피 0이므로 설정해주며,
//1~9사이 일 경우의 쉬프트 값들 모듈 완성해준다.
end
endmodule 

module adder(A,B,C,Cout); //덧셈기 구현한다.
parameter num = 6;//마티사는 6비트이므로

input [num-1:0] A,B;

output [num-1:0] C; // 덧셈 결과 값 저장
output Cout; //캐리아웃으로 발생 확인

assign { Cout, C} = A + B; // 덧셈하여 MSB는 캐리아웃값으로 지정한다.

endmodule

2/FPAddTb.v
`timescale 1 ns / 100 ps   

module FPAddTb();
    integer file,h; //파일 입력을 위한 변수
    reg [9:0] A,B; //입력
    wire [9:0] S; //출력
    wire Cout;
    
    integer i,n; //반복횟수를 결정하기 위한 변수 
    real A_dec,B_dec, S_dec;//실수값 저장
    
    FPAdd UUT(A, B, S, Cout); //모듈 불러오기
    
    initial begin       
        $dumpfile("test.vcd"); //test파일 생성
        $dumpvars(0, FPAddTb); 

        file = $fopenr("input.txt");   //txt파일을 받아오기 위해 $fopenr 함수 이용
        h = $fscanf(file,"%d\n",n); // $fscanf 함수 이용하여 첫번째줄의 값을 n 변수에 저장

        for(i=1;i<n+1;i++)begin //n회만큼 반복
            h = $fscanf(file,"%b %b\n",A,B); //다음줄의 값 두개를 각각 A, B변수에 저장
            #1 
            A_dec= ((2**0)+(A[5]*0.5)+(A[4]*0.25)+(A[3]*0.125)+
                    (A[2]*0.0625)+(A[1]*0.03125)+(A[0]*0.015625))*2**(A[9:6]); //A,B,S의 이진수값을 10진수로 변환하여 저장한다. 이하동일
            B_dec= ((2**0)+(B[5]*0.5)+(B[4]*0.25)+(B[3]*0.125)+
                    (B[2]*0.0625)+(B[1]*0.03125)+(B[0]*0.015625))*2**(B[9:6]); 
            S_dec= ((2**0)+(S[5]*0.5)+(S[4]*0.25)+(S[3]*0.125)+
                    (S[2]*0.0625)+(S[1]*0.03125)+(S[0]*0.015625))*2**(S[9:6]);
            $display("[#%2d] A=0b%b,%4f B=0b%b,%4f C=0b%b,%4f",i,A,A_dec,B,B_dec,S,S_dec); //A,B,S의 이진수와 십진수값을 출력한다 
        end

        
    end

endmodule

2/test.vcd
$date
	Sat Apr 30 12:44:14 2022
$end
$version
	Icarus Verilog
$end
$timescale
	100ps
$end
$scope module FPAddTb $end
$var wire 10 ! S [9:0] $end
$var wire 1 " Cout $end
$var reg 10 # A [9:0] $end
$var reg 10 $ B [9:0] $end
$var real 1 % A_dec $end
$var real 1 & B_dec $end
$var real 1 ' S_dec $end
$var integer 32 ( file [31:0] $end
$var integer 32 ) h [31:0] $end
$var integer 32 * i [31:0] $end
$var integer 32 + n [31:0] $end
$scope module UUT $end
$var wire 10 , A [9:0] $end
$var wire 10 - B [9:0] $end
$var wire 4 . EO [3:0] $end
$var wire 4 / num5 [3:0] $end
$var wire 4 0 num1 [3:0] $end
$var wire 10 1 Out [9:0] $end
$var wire 6 2 MO [5:0] $end
$var wire 6 3 MB1 [5:0] $end
$var wire 6 4 MB [5:0] $end
$var wire 6 5 MA [5:0] $end
$var wire 10 6 FO [9:0] $end
$var wire 10 7 FB [9:0] $end
$var wire 4 8 EB [3:0] $end
$var wire 4 9 EA [3:0] $end
$var wire 4 : E1 [3:0] $end
$var wire 1 " Cout $end
$scope module Bshi $end
$var wire 10 ; Din [9:0] $end
$var wire 4 < num [3:0] $end
$var reg 10 = Dout [9:0] $end
$var reg 10 > x1 [9:0] $end
$var reg 10 ? x2 [9:0] $end
$var reg 10 @ x3 [9:0] $end
$var reg 10 A x4 [9:0] $end
$var reg 10 B x5 [9:0] $end
$var reg 10 C x6 [9:0] $end
$var reg 10 D x7 [9:0] $end
$var reg 10 E x8 [9:0] $end
$var reg 10 F x9 [9:0] $end
$upscope $end
$scope module Oshi $end
$var wire 10 G Din [9:0] $end
$var wire 4 H num [3:0] $end
$var reg 10 I Dout [9:0] $end
$var reg 10 J x1 [9:0] $end
$var reg 10 K x2 [9:0] $end
$var reg 10 L x3 [9:0] $end
$var reg 10 M x4 [9:0] $end
$var reg 10 N x5 [9:0] $end
$var reg 10 O x6 [9:0] $end
$var reg 10 P x7 [9:0] $end
$var reg 10 Q x8 [9:0] $end
$var reg 10 R x9 [9:0] $end
$upscope $end
$scope module abadder $end
$var wire 6 S A [5:0] $end
$var wire 6 T B [5:0] $end
$var wire 1 " Cout $end
$var wire 6 U C [5:0] $end
$upscope $end
$upscope $end
$upscope $end
$enddefinitions $end
#0
$dumpvars
b100011 U
b0 T
b100011 S
b1001100011 R
b1001100011 Q
b1001100011 P
b1001100011 O
b1001100011 N
b1001100011 M
b1001100011 L
b1001100011 K
b1001100011 J
b1001100011 I
b0 H
b1001100011 G
b1011100011 F
b1011100011 E
b1011100011 D
b1011100011 C
b1011100011 B
b1011100011 A
b1011100011 @
b1011100011 ?
b1011100011 >
b0 =
b1110 <
b1011100011 ;
b1001 :
b1001 9
b1011 8
b0 7
b1001100011 6
b100011 5
b100011 4
b0 3
b100011 2
b1001100011 1
b1110 0
b0 /
b1001 .
b1011100011 -
b1001100011 ,
b1000 +
b1 *
b10 )
b10000000000000000000000000000011 (
r0 '
r0 &
r0 %
b1011100011 $
b1001100011 #
0"
b1001100011 !
$end
#10
b10100 3
b10100 T
b1001010111 !
b1001010111 1
b1001010111 I
b1001010111 R
b1001010111 Q
b1001010111 P
b1001010111 O
b1001010111 N
b1001010111 M
b1001010111 L
b1001010111 K
b1001010111 J
b1010010100 7
b1010010100 =
b1001010111 6
b1001010111 G
b10111 2
b10111 U
b10100 4
b1111 0
b1111 <
b1010 8
b1010010100 F
b1010010100 E
b1010010100 D
b1010010100 C
b1010010100 B
b1010010100 A
b1010010100 @
b1010010100 ?
b1010010100 >
b11 5
b11 S
b1010010100 $
b1010010100 -
b1010010100 ;
b1001000011 #
b1001000011 ,
b10 *
r792 '
r3168 &
r792 %
#20
b1001010100 !
b1001010100 1
b1001010100 I
b1001010100 R
b1001010100 Q
b1001010100 P
b1001010100 O
b1001010100 N
b1001010100 M
b1001010100 L
b1001010100 K
b1001010100 J
b1101 3
b1101 T
b1001010100 6
b1001010100 G
b10100 2
b10100 U
b1101 4
b0 8
b1101 7
b1101 =
b1101 F
b1101 E
b1101 D
b1101 C
b1101 B
b1101 A
b1101 @
b1101 ?
b1101 >
b111 5
b111 S
b0 0
b0 <
b0 9
b1101 $
b1101 -
b1101 ;
b111 #
b111 ,
b11 *
r696 '
r1344 &
r536 %
#30
b101001011 !
b101001011 1
b101001011 I
b101001011 R
b101001011 Q
b101001011 P
b101001011 O
b101001011 N
b101001011 M
b101001011 L
b101001011 K
b101001011 J
b1010 :
b1 /
b1 H
b100001 3
b100001 T
b1010010110 6
b1010010110 G
b10110 2
b10110 U
1"
b100001 4
b1010 8
b1010100001 7
b1010100001 =
b1010100001 F
b1010100001 E
b1010100001 D
b1010100001 C
b1010100001 B
b1010100001 A
b1010100001 @
b1010100001 ?
b1010100001 >
b110101 5
b110101 S
b0 0
b0 <
b1010 9
b1010100001 $
b1010100001 -
b1010100001 ;
b1010110101 #
b1010110101 ,
b100 *
r672 '
r1.203125 &
r1.109375 %
#40
b1001 :
b0 /
b0 H
0"
b1001110101 !
b1001110101 1
b1001110101 I
b1001110101 R
b1001110101 Q
b1001110101 P
b1001110101 O
b1001110101 N
b1001110101 M
b1001110101 L
b1001110101 K
b1001110101 J
b101 3
b101 T
b1001110101 6
b1001110101 G
b110101 2
b110101 U
b101 4
b10 8
b10000101 7
b10000101 =
b10000101 F
b10000101 E
b10000101 D
b10000101 C
b10000101 B
b10000101 A
b10000101 @
b10000101 ?
b10000101 >
b110000 5
b110000 S
b1111 0
b1111 <
b1 9
b10000101 $
b10000101 -
b10000101 ;
b1110000 #
b1110000 ,
b101 *
r37.5 '
r1552 &
r1872 %
#50
b1001111110 !
b1001111110 1
b1001111110 I
b1001111110 R
b1001111110 Q
b1001111110 P
b1001111110 O
b1001111110 N
b1001111110 M
b1001111110 L
b1001111110 K
b1001111110 J
b1001 :
b0 /
b0 H
b0 3
b0 T
b1001111110 6
b1001111110 G
b111110 2
b111110 U
0"
b1001 4
b1000 8
b0 7
b0 =
b1000001001 F
b1000001001 E
b1000001001 D
b1000001001 C
b1000001001 B
b1000001001 A
b1000001001 @
b1000001001 ?
b1000001001 >
b111110 5
b111110 S
b1010 0
b1010 <
b10 9
b1000001001 $
b1000001001 -
b1000001001 ;
b10111110 #
b10111110 ,
b110 *
r936 '
r4.3125 &
r3.5 %
#60
b1010 :
b1 /
b1 H
1"
b101010100 !
b101010100 1
b101010100 I
b101010100 R
b101010100 Q
b101010100 P
b101010100 O
b101010100 N
b101010100 M
b101010100 L
b101010100 K
b101010100 J
b110000 3
b110000 T
b1010101000 6
b1010101000 G
b101000 2
b101000 U
b110000 4
b1111 8
b1111110000 7
b1111110000 =
b1111110000 F
b1111110000 E
b1111110000 D
b1111110000 C
b1111110000 B
b1111110000 A
b1111110000 @
b1111110000 ?
b1111110000 >
b111000 5
b111000 S
b0 0
b0 <
b1111 9
b1111110000 $
b1111110000 -
b1111110000 ;
b1111111000 #
b1111111000 ,
b111 *
r1008 '
r292 &
r7.875 %
#70
b1001 :
b0 /
b0 H
0"
b1001110000 !
b1001110000 1
b1001110000 I
b1001110000 R
b1001110000 Q
b1001110000 P
b1001110000 O
b1001110000 N
b1001110000 M
b1001110000 L
b1001110000 K
b1001110000 J
b10000 3
b10000 T
b1001110000 6
b1001110000 G
b110000 2
b110000 U
b100000 4
b1 0
b1 <
b1110 8
b111010000 7
b111010000 =
b111010000 F
b111010000 E
b111010000 D
b111010000 C
b111010000 B
b111010000 A
b111010000 @
b111010000 ?
b111010000 >
b100000 5
b100000 S
b1110100000 $
b1110100000 -
b1110100000 ;
b1111100000 #
b1111100000 ,
b1000 *
r42 '
r57344 &
r61440 %
#80
b1001 *
r896 '
r24576 &
r49152 %
